fourlabs_auth/__init__.py
fourlabs_auth/admin.py
fourlabs_auth/apps.py
fourlabs_auth/conf.py
fourlabs_auth/forms.py
fourlabs_auth/models.py
fourlabs_auth/urls.py
fourlabs_auth/views.py
fourlabs_auth/migrations/__init__.py
fourlabs_auth/services/__init__.py
fourlabs_auth/services/send_mail.py
fourlabs_auth/services/token_manager.py
fourlabs_auth-0.1.18.dist-info/METADATA
fourlabs_auth-0.1.18.dist-info/WHEEL
fourlabs_auth-0.1.18.dist-info/top_level.txt
fourlabs_auth-0.1.18.dist-info/RECORD
